nx_altair/__init__.py
nx_altair/__version__.py
nx_altair/_utils.py
nx_altair/core.py
nx_altair/draw_altair.py
nx_altair-0.1.6.dist-info/LICENSE
nx_altair-0.1.6.dist-info/METADATA
nx_altair-0.1.6.dist-info/WHEEL
nx_altair-0.1.6.dist-info/top_level.txt
nx_altair-0.1.6.dist-info/RECORD
