Metadata-Version: 2.1
Name: nx-altair
Version: 0.1.6
Summary: Draw NetworkX graphs with Altair
Home-page: https://github.com/Zsailer/nx_altair
Author: Zachary R. Sailer
Author-email: zachsailer@gmail.com
License: MIT
Platform: UNKNOWN
Classifier: License :: OSI Approved :: MIT License
Classifier: Programming Language :: Python
Classifier: Programming Language :: Python :: 3
Classifier: Programming Language :: Python :: 3.6
Classifier: Programming Language :: Python :: Implementation :: CPython
Classifier: Programming Language :: Python :: Implementation :: PyPy
Requires-Python: >=3.3.0
Requires-Dist: pandas
Requires-Dist: networkx
Requires-Dist: altair
